{
    "metadata": {
        "run_id": "20250905-141440_baseline",
        "suite": "short_pos",
        "label": "baseline",
        "commit_sha": "de0ca5a",
        "branch": "feature/performance-measurement",
        "go_version": "go version go1.22.5 linux/amd64",
        "ffmpeg_version": "ffmpeg version 7.0.2-static https://johnvansickle.com/ffmpeg/  Copyright (c) 2000-2024 the FFmpeg developers",
        "os": "linux",
        "arch": "amd64",
        "cli_args": "-i resources/samples/sample_yes.mp4 -o runs/perf -a -s 0.4 -f",
        "timestamp_iso": "2025-09-05T14:14:40+02:00"
    },
    "timings_ms": {
        "total_ms": 5007.411,
        "stages_ms": {
            "auto_thresholds": 0.083,
            "video_analysis": 4997.182,
            "video_detection": 8.644
        }
    },
    "bench": {
        "ns_per_op": 4960855785,
        "bytes_per_op": 15264,
        "allocs_per_op": 49
    },
    "detections": 6
}
